withtimer/__about__.py
withtimer/__init__.py
withtimer/version.py
withtimer/withtimer.py
withtimer/config/default.yaml
withtimer-0.1.0.dev1.dist-info/LICENSE
withtimer-0.1.0.dev1.dist-info/METADATA
withtimer-0.1.0.dev1.dist-info/WHEEL
withtimer-0.1.0.dev1.dist-info/top_level.txt
withtimer-0.1.0.dev1.dist-info/RECORD
