Metadata-Version: 2.1
Name: withtimer
Version: 0.1.0.dev1
Summary: Simple Python Timer class you can wrap around blocks of code you want to benchmark
Home-page: https://github.com/zcutlip/withtimer
Author: Zachary Cutlip
License: MIT
Platform: UNKNOWN
Requires-Python: >=2.7
